stratmc/__init__.py
stratmc/config.py
stratmc/data.py
stratmc/inference.py
stratmc/model.py
stratmc/plotting.py
stratmc/synthetics.py
stratmc/tests.py
stratmc-1.0.0.dist-info/licenses/LICENSE
stratmc-1.0.0.dist-info/METADATA
stratmc-1.0.0.dist-info/WHEEL
stratmc-1.0.0.dist-info/top_level.txt
stratmc-1.0.0.dist-info/RECORD
