Metadata-Version: 2.4
Name: stratmc
Version: 1.0.0
Summary: Bayesian statistical framework for reconstructing past Earth system change from the stratigraphic record
Author-email: Stacey Edmonsond <staceyedmonsond777@gmail.com>
License: GNU GENERAL PUBLIC LICENSE
Project-URL: Repository, https://github.com/sedmonsond/stratmc
Project-URL: Documentation, https://stratmc.readthedocs.io
Keywords: Bayesian inference,stratigraphy,geochemistry,Earth history,stratigraphic correlation,chemostratigraphy
Classifier: Development Status :: 4 - Beta
Classifier: Programming Language :: Python
Classifier: Programming Language :: Python :: 3.10
Classifier: Programming Language :: Python :: 3.11
Classifier: Programming Language :: Python :: 3.12
Classifier: Intended Audience :: Science/Research
Classifier: Topic :: Scientific/Engineering
Classifier: Operating System :: OS Independent
Requires-Python: >=3.10
License-File: LICENSE
Requires-Dist: blackjax
Requires-Dist: fastprogress
Requires-Dist: ipywidgets
Requires-Dist: jax
Requires-Dist: matplotlib<=3.9.0
Requires-Dist: netCDF4
Requires-Dist: numpyro
Requires-Dist: pymc>=5.19
Requires-Dist: scikit-learn
Requires-Dist: scipy
Requires-Dist: seaborn
Requires-Dist: tqdm
Requires-Dist: xarray
Provides-Extra: dev
Requires-Dist: ipykernel; extra == "dev"
Requires-Dist: pre-commit; extra == "dev"
Provides-Extra: test
Requires-Dist: pytest; extra == "test"
Requires-Dist: pytest-cov; extra == "test"
Provides-Extra: doc
Requires-Dist: jupyter-sphinx; extra == "doc"
Requires-Dist: myst-nb; extra == "doc"
Requires-Dist: numpydoc; extra == "doc"
Requires-Dist: pydata-sphinx-theme; extra == "doc"
Requires-Dist: sphinx>=4.5; extra == "doc"
Requires-Dist: sphinx-copybutton; extra == "doc"
Requires-Dist: sphinx-design; extra == "doc"
Requires-Dist: sphinx_inline_tabs; extra == "doc"
Requires-Dist: sphinx-notfound-page; extra == "doc"
Requires-Dist: sphinxext-rediraffe; extra == "doc"
Requires-Dist: sphinx-remove-toctrees; extra == "doc"
Requires-Dist: sphinx-togglebutton; extra == "doc"
Requires-Dist: watermark; extra == "doc"
Dynamic: license-file
